{
  "longueurs": {
    "LUXE_3D": {
      "160": "-14.5",
      "161": "-14",
      "162": "-13.5",
      "163": "-13",
      "164": "-12.5",
      "165": "-12",
      "166": "-11.5",
      "167": "-11",
      "168": "-10.5",
      "169": "-10",
      "170": "-9.5",
      "171": "-9",
      "172": "-8.5",
      "173": "-8",
      "174": "-7.5",
      "175": "-7",
      "176": "-6.5",
      "177": "-6",
      "178": "-5.5",
      "179": "-5",
      "180": "-4.5",
      "181": "-4",
      "182": "-3.5",
      "183": "-3",
      "184": "-2.5",
      "185": "-2",
      "186": "-1.5",
      "187": "-1",
      "188": "-0.5",
      "189": "0",
      "190": "0.5",
      "191": "1",
      "192": "1.5",
      "193": "2",
      "194": "2.5",
      "195": "3",
      "196": "3.5",
      "197": "4",
      "198": "4.5",
      "199": "5",
      "200": "5.5",
      "201": "6",
      "202": "6.5",
      "203": "7",
      "204": "7.5",
      "205": "8",
      "206": "8.5",
      "207": "9",
      "208": "9.5",
      "209": "10",
      "210": "10.5",
      "211": "11",
      "212": "11.5",
      "213": "12",
      "214": "12.5",
      "215": "13",
      "216": "13.5",
      "217": "14",
      "218": "14.5",
      "219": "15",
      "220": "15.5",
      "221": "16",
      "222": "16.5",
      "223": "17",
      "224": "17.5",
      "225": "18",
      "226": "18.5",
      "227": "19",
      "228": "19.5",
      "229": "20",
      "230": "20.5",
      "231": "21",
      "232": "21.5",
      "233": "22",
      "234": "22.5",
      "235": "23",
      "236": "23.5",
      "237": "24",
      "238": "24.5",
      "239": "25",
      "240": "25.5",
      "241": "26",
      "242": "26.5",
      "243": "27",
      "244": "27.5",
      "245": "28",
      "246": "28.5",
      "247": "29",
      "248": "29.5",
      "249": "30",
      "250": "30.5",
      "251": "31"
    },
    "TENCEL": {
      "160": "-11.5",
      "161": "-11",
      "162": "-10.5",
      "163": "-10",
      "164": "-9.5",
      "165": "-9",
      "166": "-8.5",
      "167": "-8",
      "168": "-7.5",
      "169": "-7",
      "170": "-6.5",
      "171": "-6",
      "172": "-5.5",
      "173": "-5",
      "174": "-4.5",
      "175": "-4",
      "176": "-3.5",
      "177": "-3",
      "178": "-2.5",
      "179": "-2",
      "180": "-1.5",
      "181": "-1",
      "182": "-0.5",
      "183": "0",
      "184": "0.5",
      "185": "1",
      "186": "1.5",
      "187": "2",
      "188": "2.5",
      "189": "3",
      "190": "3.5",
      "191": "4",
      "192": "4.5",
      "193": "5",
      "194": "5.5",
      "195": "6",
      "196": "6.5",
      "197": "7",
      "198": "7.5",
      "199": "8",
      "200": "8.5",
      "201": "9",
      "202": "9.5",
      "203": "10",
      "204": "10.5",
      "205": "11",
      "206": "11.5",
      "207": "12",
      "208": "12.5",
      "209": "13",
      "210": "13.5",
      "211": "14",
      "212": "14.5",
      "213": "15",
      "214": "15.5",
      "215": "16",
      "216": "16.5",
      "217": "17",
      "218": "17.5",
      "219": "18",
      "220": "18.5",
      "221": "19",
      "222": "19.5",
      "223": "20",
      "224": "20.5",
      "225": "21",
      "226": "21.5",
      "227": "22",
      "228": "22.5",
      "229": "23",
      "230": "23.5",
      "231": "24",
      "232": "24.5",
      "233": "25",
      "234": "25.5",
      "235": "26",
      "236": "26.5",
      "237": "27",
      "238": "27.5",
      "239": "28",
      "240": "28.5",
      "241": "29",
      "242": "29.5",
      "243": "30",
      "244": "30.5",
      "245": "31",
      "246": "31.5",
      "247": "32",
      "248": "32.5",
      "249": "33",
      "250": "33.5",
      "251": "34"
    },
    "POLY": {
      "160": "172",
      "161": "173",
      "162": "174",
      "163": "175",
      "164": "176",
      "165": "177",
      "166": "178",
      "167": "179",
      "168": "180",
      "169": "181",
      "170": "182",
      "171": "183",
      "172": "184",
      "173": "185",
      "174": "186",
      "175": "187",
      "176": "188",
      "177": "189",
      "178": "190",
      "179": "191",
      "180": "192",
      "181": "193",
      "182": "194",
      "183": "195",
      "184": "196",
      "185": "197",
      "186": "198",
      "187": "199",
      "188": "200",
      "189": "201",
      "190": "202",
      "191": "203",
      "192": "204",
      "193": "205",
      "194": "206",
      "195": "207",
      "196": "208",
      "197": "209",
      "198": "210",
      "199": "211",
      "200": "212",
      "201": "213",
      "202": "214",
      "203": "215",
      "204": "216",
      "205": "217",
      "206": "218",
      "207": "219",
      "208": "220",
      "209": "221",
      "210": "222",
      "211": "223",
      "212": "224",
      "213": "225",
      "214": "226",
      "215": "227",
      "216": "228",
      "217": "229",
      "218": "230",
      "219": "231",
      "220": "232",
      "221": "233",
      "222": "234",
      "223": "235",
      "224": "236",
      "225": "237",
      "226": "238",
      "227": "239",
      "228": "240",
      "229": "241",
      "230": "242",
      "231": "243",
      "232": "244",
      "233": "245",
      "234": "246",
      "235": "247",
      "236": "248",
      "237": "249",
      "238": "250",
      "239": "251",
      "240": "252",
      "241": "253",
      "242": "254",
      "243": "255",
      "244": "256",
      "245": "257",
      "246": "258",
      "247": "259",
      "248": "260",
      "249": "261",
      "250": "262",
      "251": "263"
    }
  }
}
